project_snap/__init__.py
project_snap/__main__.py
project_snap/core.py
project_snap/main.py
project_snap/utils.py
project_snap-1.0.0.dist-info/LICENSE
project_snap-1.0.0.dist-info/METADATA
project_snap-1.0.0.dist-info/WHEEL
project_snap-1.0.0.dist-info/entry_points.txt
project_snap-1.0.0.dist-info/top_level.txt
project_snap-1.0.0.dist-info/RECORD
