Metadata-Version: 2.1
Name: project-snap
Version: 1.0.0
Summary: A utility to create Markdown snapshots of project structures for LLMs
Home-page: https://github.com/still_standing88/project-snap/
Author: still-standing88
License: MIT
Keywords: project snapshot markdown llm documentation
Classifier: Development Status :: 4 - Beta
Classifier: Environment :: Console
Classifier: Intended Audience :: Developers
Classifier: License :: OSI Approved :: MIT License
Classifier: Programming Language :: Python :: 3
Classifier: Programming Language :: Python :: 3.6
Classifier: Programming Language :: Python :: 3.7
Classifier: Programming Language :: Python :: 3.8
Classifier: Programming Language :: Python :: 3.9
Classifier: Programming Language :: Python :: 3.10
Classifier: Topic :: Software Development :: Documentation
Classifier: Topic :: Utilities
Requires-Python: >=3.6
License-File: LICENSE
